libtobiiglassesctrl/__init__.py
libtobiiglassesctrl/controller.py
libtobiiglassesctrl-2.4.3.dist-info/LICENSE
libtobiiglassesctrl-2.4.3.dist-info/METADATA
libtobiiglassesctrl-2.4.3.dist-info/WHEEL
libtobiiglassesctrl-2.4.3.dist-info/RECORD
