Metadata-Version: 2.1
Name: libtobiiglassesctrl
Version: 2.4.3
Summary: A Python controller for Tobii Pro Glasses 2
Home-page: https://github.com/nastaran62/LibTobiiGlassesPyController/
License: GPL-3.0-or-later
Keywords: eye-tracker,tobii,glasses,tobii pro glasses 2,tobii glasses,eye tracking
Author: Davide De Tommaso
Requires-Python: >=3.8,<3.13
Classifier: License :: OSI Approved :: GNU General Public License v3 or later (GPLv3+)
Classifier: Programming Language :: Python :: 3
Classifier: Programming Language :: Python :: 3.8
Classifier: Programming Language :: Python :: 3.9
Classifier: Programming Language :: Python :: 3.10
Classifier: Programming Language :: Python :: 3.11
Classifier: Programming Language :: Python :: 3.12
Requires-Dist: netifaces (==0.11.0)
